cachein/__init__.py
cachein/forward.py
cachein/manager.py
cachein/member.py
cachein-0.3.2.dist-info/LICENSE
cachein-0.3.2.dist-info/METADATA
cachein-0.3.2.dist-info/WHEEL
cachein-0.3.2.dist-info/top_level.txt
cachein-0.3.2.dist-info/RECORD
