Metadata-Version: 2.1
Name: cachein
Version: 0.3.2
Summary: Lazy caching, delegation, and more
Home-page: https://gitlab.com/hrharkins/python-cachein
Author: Rich Harkins
Author-email: rich.harkins@gmail.com
License: UNKNOWN
Platform: UNKNOWN
Classifier: Programming Language :: Python :: 3
Classifier: License :: OSI Approved :: MIT License
Classifier: Operating System :: OS Independent
Requires-Python: >=3.6
